basic_eda/__init__.py
basic_eda/categorical.py
basic_eda/eda.py
basic_eda/generator.py
basic_eda/heatmap.py
basic_eda/numeric.py
basic_eda/pair_numeric.py
basic_eda/utils.py
basic_eda-0.3.dist-info/LICENSE
basic_eda-0.3.dist-info/METADATA
basic_eda-0.3.dist-info/WHEEL
basic_eda-0.3.dist-info/top_level.txt
basic_eda-0.3.dist-info/RECORD
