Metadata-Version: 2.1
Name: basic-eda
Version: 0.3
Summary: Simple Exploratory Data Analysis tool.
Home-page: https://github.com/darkhan-ai/basic-eda
License: MIT
License-File: LICENSE
Requires-Dist: pandas
Requires-Dist: matplotlib
Requires-Dist: seaborn
Requires-Dist: joblib
Requires-Dist: tqdm
